Metadata-Version: 2.1
Name: sensor-gateway
Version: 0.3
Summary: sensor gateway for data collection
Home-page: https://github.com/nbdy/sensor_gateway
Author: Pascal Eberlein
Author-email: pascal@eberlein.io
License: UNKNOWN
Keywords: sensor gateway data collection
Platform: UNKNOWN
Classifier: Intended Audience :: Developers
Classifier: Topic :: Software Development :: Build Tools
Classifier: License :: OSI Approved :: MIT License
